README.md
pyproject.toml
setup.py
smorest_crud/__init__.py
smorest_crud/view.py
smorest_crud.egg-info/PKG-INFO
smorest_crud.egg-info/SOURCES.txt
smorest_crud.egg-info/dependency_links.txt
smorest_crud.egg-info/not-zip-safe
smorest_crud.egg-info/requires.txt
smorest_crud.egg-info/top_level.txt