Metadata-Version: 2.1
Name: smorest-crud
Version: 0.0.7
Summary: Reusable CRUD endpoints using flask-smorest, flask-jwt-extended, and SQLAlchemy.
Home-page: https://github.com/jetbridge/smorest-crud
Author: JetBridge
Author-email: me@mish.dev
License: MIT
Platform: any
Requires-Python: >=3.6.0
